a2pm/__init__.py
a2pm/a2pm.py
a2pm/callbacks/__init__.py
a2pm/callbacks/base_callback.py
a2pm/callbacks/metric_callback.py
a2pm/callbacks/time_callback.py
a2pm/patterns/__init__.py
a2pm/patterns/base_pattern.py
a2pm/patterns/combination_pattern.py
a2pm/patterns/interval_pattern.py
a2pm/patterns/patterns.py
a2pm/wrappers/__init__.py
a2pm/wrappers/base_wrapper.py
a2pm/wrappers/keras_wrapper.py
a2pm/wrappers/sklearn_wrapper.py
a2pm/wrappers/torch_wrapper.py
a2pm-1.2.0.dist-info/LICENSE.txt
a2pm-1.2.0.dist-info/METADATA
a2pm-1.2.0.dist-info/WHEEL
a2pm-1.2.0.dist-info/top_level.txt
a2pm-1.2.0.dist-info/RECORD
