Metadata-Version: 2.1
Name: a2pm
Version: 1.2.0
Summary: Adaptative Perturbation Pattern Method
Home-page: https://github.com/vitorinojoao/a2pm
Author: João Vitorino
Author-email: jpmvo@outlook.com
License: MIT
Project-URL: Article, https://doi.org/10.3390/fi14040108
Project-URL: Documentation, https://a2pm.readthedocs.io/en/latest/
Platform: UNKNOWN
Classifier: License :: OSI Approved
Classifier: License :: OSI Approved :: MIT License
Classifier: Programming Language :: Python
Classifier: Programming Language :: Python :: 3
Classifier: Operating System :: OS Independent
Classifier: Intended Audience :: Science/Research
Classifier: Intended Audience :: Developers
Classifier: Topic :: Adaptive Technologies
Classifier: Topic :: Scientific/Engineering
Classifier: Topic :: Scientific/Engineering :: Artificial Intelligence
Classifier: Topic :: Software Development
Classifier: Topic :: Software Development :: Libraries
Classifier: Topic :: Software Development :: Libraries :: Python Modules
Requires-Python: >=3.5
License-File: LICENSE.txt
Requires-Dist: numpy (<2,>=1.17.5)
Requires-Dist: scikit-learn (<2,>=0.23.2)
